<?xml version="1.0" ?>
<annotation>
	<filename>Frame_756.jpg</filename>
	<size>
		<width>1920</width>
		<height>1080</height>
		<depth>3</depth>
	</size>
	<object>
		<name>Central Incisor</name>
		<pose/>
		<truncated/>
		<difficult/>
		<bndbox>
			<xmin>455</xmin>
			<xmax>724</xmax>
			<ymin>204</ymin>
			<ymax>614</ymax>
		</bndbox>
	</object>
	<object>
		<name>Central Incisor</name>
		<pose/>
		<truncated/>
		<difficult/>
		<bndbox>
			<xmin>199</xmin>
			<xmax>455</xmax>
			<ymin>207</ymin>
			<ymax>614</ymax>
		</bndbox>
	</object>
	<object>
		<name>Lateral Incisor</name>
		<pose/>
		<truncated/>
		<difficult/>
		<bndbox>
			<xmin>724</xmin>
			<xmax>996</xmax>
			<ymin>193</ymin>
			<ymax>601</ymax>
		</bndbox>
	</object>
	<object>
		<name>Lateral Incisor</name>
		<pose/>
		<truncated/>
		<difficult/>
		<bndbox>
			<xmin>0</xmin>
			<xmax>199</xmax>
			<ymin>207</ymin>
			<ymax>639</ymax>
		</bndbox>
	</object>
	<object>
		<name>Canine</name>
		<pose/>
		<truncated/>
		<difficult/>
		<bndbox>
			<xmin>989</xmin>
			<xmax>1258</xmax>
			<ymin>116</ymin>
			<ymax>657</ymax>
		</bndbox>
	</object>
	<object>
		<name>1st Premolar</name>
		<pose/>
		<truncated/>
		<difficult/>
		<bndbox>
			<xmin>1240</xmin>
			<xmax>1476</xmax>
			<ymin>114</ymin>
			<ymax>573</ymax>
		</bndbox>
	</object>
	<object>
		<name>2nd Premolar</name>
		<pose/>
		<truncated/>
		<difficult/>
		<bndbox>
			<xmin>1424</xmin>
			<xmax>1623</xmax>
			<ymin>112</ymin>
			<ymax>476</ymax>
		</bndbox>
	</object>
</annotation>
