<?xml version="1.0" ?>
<annotation>
	<filename>Frame_544.jpg</filename>
	<size>
		<width>1920</width>
		<height>1080</height>
		<depth>3</depth>
	</size>
	<object>
		<name>Central Incisor</name>
		<pose/>
		<truncated/>
		<difficult/>
		<bndbox>
			<xmin>939</xmin>
			<xmax>1469</xmax>
			<ymin>157</ymin>
			<ymax>770</ymax>
		</bndbox>
	</object>
	<object>
		<name>Central Incisor</name>
		<pose/>
		<truncated/>
		<difficult/>
		<bndbox>
			<xmin>425</xmin>
			<xmax>937</xmax>
			<ymin>189</ymin>
			<ymax>759</ymax>
		</bndbox>
	</object>
	<object>
		<name>Lateral Incisor</name>
		<pose/>
		<truncated/>
		<difficult/>
		<bndbox>
			<xmin>1473</xmin>
			<xmax>1811</xmax>
			<ymin>166</ymin>
			<ymax>721</ymax>
		</bndbox>
	</object>
	<object>
		<name>Lateral Incisor</name>
		<pose/>
		<truncated/>
		<difficult/>
		<bndbox>
			<xmin>95</xmin>
			<xmax>425</xmax>
			<ymin>193</ymin>
			<ymax>721</ymax>
		</bndbox>
	</object>
	<object>
		<name>Canine</name>
		<pose/>
		<truncated/>
		<difficult/>
		<bndbox>
			<xmin>1813</xmin>
			<xmax>1920</xmax>
			<ymin>284</ymin>
			<ymax>689</ymax>
		</bndbox>
	</object>
	<object>
		<name>Canine</name>
		<pose/>
		<truncated/>
		<difficult/>
		<bndbox>
			<xmin>0</xmin>
			<xmax>92</xmax>
			<ymin>309</ymin>
			<ymax>791</ymax>
		</bndbox>
	</object>
</annotation>
