<?xml version="1.0" ?>
<annotation>
	<filename>Frame_594.jpg</filename>
	<size>
		<width>1920</width>
		<height>1080</height>
		<depth>3</depth>
	</size>
	<object>
		<name>Central Incisor</name>
		<pose/>
		<truncated/>
		<difficult/>
		<bndbox>
			<xmin>971</xmin>
			<xmax>1503</xmax>
			<ymin>103</ymin>
			<ymax>700</ymax>
		</bndbox>
	</object>
	<object>
		<name>Central Incisor</name>
		<pose/>
		<truncated/>
		<difficult/>
		<bndbox>
			<xmin>448</xmin>
			<xmax>973</xmax>
			<ymin>127</ymin>
			<ymax>696</ymax>
		</bndbox>
	</object>
	<object>
		<name>Lateral Incisor</name>
		<pose/>
		<truncated/>
		<difficult/>
		<bndbox>
			<xmin>1503</xmin>
			<xmax>1858</xmax>
			<ymin>109</ymin>
			<ymax>664</ymax>
		</bndbox>
	</object>
	<object>
		<name>Lateral Incisor</name>
		<pose/>
		<truncated/>
		<difficult/>
		<bndbox>
			<xmin>126</xmin>
			<xmax>448</xmax>
			<ymin>139</ymin>
			<ymax>648</ymax>
		</bndbox>
	</object>
	<object>
		<name>Canine</name>
		<pose/>
		<truncated/>
		<difficult/>
		<bndbox>
			<xmin>1858</xmin>
			<xmax>1920</xmax>
			<ymin>293</ymin>
			<ymax>585</ymax>
		</bndbox>
	</object>
	<object>
		<name>Canine</name>
		<pose/>
		<truncated/>
		<difficult/>
		<bndbox>
			<xmin>0</xmin>
			<xmax>126</xmax>
			<ymin>213</ymin>
			<ymax>736</ymax>
		</bndbox>
	</object>
</annotation>
