<?xml version="1.0" ?>
<annotation>
	<filename>Frame_14.jpg</filename>
	<size>
		<width>1920</width>
		<height>1080</height>
		<depth>3</depth>
	</size>
	<object>
		<name>Central Incisor</name>
		<pose/>
		<truncated/>
		<difficult/>
		<bndbox>
			<xmin>932</xmin>
			<xmax>1256</xmax>
			<ymin>247</ymin>
			<ymax>619</ymax>
		</bndbox>
	</object>
	<object>
		<name>Central Incisor</name>
		<pose/>
		<truncated/>
		<difficult/>
		<bndbox>
			<xmin>597</xmin>
			<xmax>923</xmax>
			<ymin>245</ymin>
			<ymax>607</ymax>
		</bndbox>
	</object>
	<object>
		<name>Lateral Incisor</name>
		<pose/>
		<truncated/>
		<difficult/>
		<bndbox>
			<xmin>1267</xmin>
			<xmax>1496</xmax>
			<ymin>238</ymin>
			<ymax>583</ymax>
		</bndbox>
	</object>
	<object>
		<name>Lateral Incisor</name>
		<pose/>
		<truncated/>
		<difficult/>
		<bndbox>
			<xmin>393</xmin>
			<xmax>597</xmax>
			<ymin>247</ymin>
			<ymax>564</ymax>
		</bndbox>
	</object>
	<object>
		<name>Canine</name>
		<pose/>
		<truncated/>
		<difficult/>
		<bndbox>
			<xmin>1503</xmin>
			<xmax>1713</xmax>
			<ymin>223</ymin>
			<ymax>601</ymax>
		</bndbox>
	</object>
	<object>
		<name>Canine</name>
		<pose/>
		<truncated/>
		<difficult/>
		<bndbox>
			<xmin>237</xmin>
			<xmax>400</xmax>
			<ymin>250</ymin>
			<ymax>619</ymax>
		</bndbox>
	</object>
	<object>
		<name>1st Premolar</name>
		<pose/>
		<truncated/>
		<difficult/>
		<bndbox>
			<xmin>1711</xmin>
			<xmax>1856</xmax>
			<ymin>288</ymin>
			<ymax>592</ymax>
		</bndbox>
	</object>
	<object>
		<name>1st Premolar</name>
		<pose/>
		<truncated/>
		<difficult/>
		<bndbox>
			<xmin>153</xmin>
			<xmax>235</xmax>
			<ymin>304</ymin>
			<ymax>603</ymax>
		</bndbox>
	</object>
	<object>
		<name>2nd Premolar</name>
		<pose/>
		<truncated/>
		<difficult/>
		<bndbox>
			<xmin>1856</xmin>
			<xmax>1919</xmax>
			<ymin>349</ymin>
			<ymax>607</ymax>
		</bndbox>
	</object>
	<object>
		<name>2nd Premolar</name>
		<pose/>
		<truncated/>
		<difficult/>
		<bndbox>
			<xmin>95</xmin>
			<xmax>153</xmax>
			<ymin>367</ymin>
			<ymax>594</ymax>
		</bndbox>
	</object>
	<object>
		<name>Central Incisor</name>
		<pose/>
		<truncated/>
		<difficult/>
		<bndbox>
			<xmin>950</xmin>
			<xmax>1150</xmax>
			<ymin>465</ymin>
			<ymax>795</ymax>
		</bndbox>
	</object>
	<object>
		<name>Central Incisor</name>
		<pose/>
		<truncated/>
		<difficult/>
		<bndbox>
			<xmin>747</xmin>
			<xmax>937</xmax>
			<ymin>449</ymin>
			<ymax>791</ymax>
		</bndbox>
	</object>
	<object>
		<name>Lateral Incisor</name>
		<pose/>
		<truncated/>
		<difficult/>
		<bndbox>
			<xmin>1159</xmin>
			<xmax>1376</xmax>
			<ymin>506</ymin>
			<ymax>818</ymax>
		</bndbox>
	</object>
	<object>
		<name>Lateral Incisor</name>
		<pose/>
		<truncated/>
		<difficult/>
		<bndbox>
			<xmin>550</xmin>
			<xmax>733</xmax>
			<ymin>472</ymin>
			<ymax>800</ymax>
		</bndbox>
	</object>
	<object>
		<name>Canine</name>
		<pose/>
		<truncated/>
		<difficult/>
		<bndbox>
			<xmin>1372</xmin>
			<xmax>1573</xmax>
			<ymin>458</ymin>
			<ymax>854</ymax>
		</bndbox>
	</object>
	<object>
		<name>Canine</name>
		<pose/>
		<truncated/>
		<difficult/>
		<bndbox>
			<xmin>344</xmin>
			<xmax>543</xmax>
			<ymin>549</ymin>
			<ymax>884</ymax>
		</bndbox>
	</object>
	<object>
		<name>1st Premolar</name>
		<pose/>
		<truncated/>
		<difficult/>
		<bndbox>
			<xmin>1566</xmin>
			<xmax>1741</xmax>
			<ymin>530</ymin>
			<ymax>841</ymax>
		</bndbox>
	</object>
	<object>
		<name>1st Premolar</name>
		<pose/>
		<truncated/>
		<difficult/>
		<bndbox>
			<xmin>228</xmin>
			<xmax>380</xmax>
			<ymin>549</ymin>
			<ymax>829</ymax>
		</bndbox>
	</object>
	<object>
		<name>2nd Premolar</name>
		<pose/>
		<truncated/>
		<difficult/>
		<bndbox>
			<xmin>1729</xmin>
			<xmax>1863</xmax>
			<ymin>528</ymin>
			<ymax>798</ymax>
		</bndbox>
	</object>
	<object>
		<name>2nd Premolar</name>
		<pose/>
		<truncated/>
		<difficult/>
		<bndbox>
			<xmin>147</xmin>
			<xmax>237</xmax>
			<ymin>589</ymin>
			<ymax>773</ymax>
		</bndbox>
	</object>
	<object>
		<name>1st Molar</name>
		<pose/>
		<truncated/>
		<difficult/>
		<bndbox>
			<xmin>1865</xmin>
			<xmax>1920</xmax>
			<ymin>589</ymin>
			<ymax>736</ymax>
		</bndbox>
	</object>
	<object>
		<name>1st Molar</name>
		<pose/>
		<truncated/>
		<difficult/>
		<bndbox>
			<xmin>24</xmin>
			<xmax>144</xmax>
			<ymin>588</ymin>
			<ymax>752</ymax>
		</bndbox>
	</object>
	<object>
		<name>1st Molar</name>
		<pose/>
		<truncated/>
		<difficult/>
		<bndbox>
			<xmin>27</xmin>
			<xmax>90</xmax>
			<ymin>492</ymin>
			<ymax>555</ymax>
		</bndbox>
	</object>
	<object>
		<name>2nd Molar</name>
		<pose/>
		<truncated/>
		<difficult/>
		<bndbox>
			<xmin>0</xmin>
			<xmax>90</xmax>
			<ymin>577</ymin>
			<ymax>719</ymax>
		</bndbox>
	</object>
</annotation>
