<?xml version="1.0" ?>
<annotation>
	<filename>Frame_873.jpg</filename>
	<size>
		<width>1920</width>
		<height>1080</height>
		<depth>3</depth>
	</size>
	<object>
		<name>Central Incisor</name>
		<pose/>
		<truncated/>
		<difficult/>
		<bndbox>
			<xmin>1621</xmin>
			<xmax>1920</xmax>
			<ymin>260</ymin>
			<ymax>756</ymax>
		</bndbox>
	</object>
	<object>
		<name>Central Incisor</name>
		<pose/>
		<truncated/>
		<difficult/>
		<bndbox>
			<xmin>1301</xmin>
			<xmax>1621</xmax>
			<ymin>267</ymin>
			<ymax>767</ymax>
		</bndbox>
	</object>
	<object>
		<name>Lateral Incisor</name>
		<pose/>
		<truncated/>
		<difficult/>
		<bndbox>
			<xmin>1021</xmin>
			<xmax>1299</xmax>
			<ymin>276</ymin>
			<ymax>819</ymax>
		</bndbox>
	</object>
	<object>
		<name>Canine</name>
		<pose/>
		<truncated/>
		<difficult/>
		<bndbox>
			<xmin>751</xmin>
			<xmax>1014</xmax>
			<ymin>246</ymin>
			<ymax>892</ymax>
		</bndbox>
	</object>
	<object>
		<name>1st Premolar</name>
		<pose/>
		<truncated/>
		<difficult/>
		<bndbox>
			<xmin>570</xmin>
			<xmax>796</xmax>
			<ymin>258</ymin>
			<ymax>722</ymax>
		</bndbox>
	</object>
	<object>
		<name>2nd Premolar</name>
		<pose/>
		<truncated/>
		<difficult/>
		<bndbox>
			<xmin>452</xmin>
			<xmax>566</xmax>
			<ymin>484</ymin>
			<ymax>652</ymax>
		</bndbox>
	</object>
	<object>
		<name>2nd Molar</name>
		<pose/>
		<truncated/>
		<difficult/>
		<bndbox>
			<xmin>362</xmin>
			<xmax>581</xmax>
			<ymin>124</ymin>
			<ymax>264</ymax>
		</bndbox>
	</object>
	<object>
		<name>3rd Molar</name>
		<pose/>
		<truncated/>
		<difficult/>
		<bndbox>
			<xmin>328</xmin>
			<xmax>498</xmax>
			<ymin>70</ymin>
			<ymax>196</ymax>
		</bndbox>
	</object>
</annotation>
