<?xml version="1.0" ?>
<annotation>
	<filename>Frame_753.jpg</filename>
	<size>
		<width>1920</width>
		<height>1080</height>
		<depth>3</depth>
	</size>
	<object>
		<name>Central Incisor</name>
		<pose/>
		<truncated/>
		<difficult/>
		<bndbox>
			<xmin>461</xmin>
			<xmax>729</xmax>
			<ymin>209</ymin>
			<ymax>621</ymax>
		</bndbox>
	</object>
	<object>
		<name>Central Incisor</name>
		<pose/>
		<truncated/>
		<difficult/>
		<bndbox>
			<xmin>203</xmin>
			<xmax>459</xmax>
			<ymin>216</ymin>
			<ymax>621</ymax>
		</bndbox>
	</object>
	<object>
		<name>Lateral Incisor</name>
		<pose/>
		<truncated/>
		<difficult/>
		<bndbox>
			<xmin>729</xmin>
			<xmax>998</xmax>
			<ymin>204</ymin>
			<ymax>619</ymax>
		</bndbox>
	</object>
	<object>
		<name>Lateral Incisor</name>
		<pose/>
		<truncated/>
		<difficult/>
		<bndbox>
			<xmin>0</xmin>
			<xmax>203</xmax>
			<ymin>211</ymin>
			<ymax>644</ymax>
		</bndbox>
	</object>
	<object>
		<name>Canine</name>
		<pose/>
		<truncated/>
		<difficult/>
		<bndbox>
			<xmin>996</xmin>
			<xmax>1274</xmax>
			<ymin>130</ymin>
			<ymax>673</ymax>
		</bndbox>
	</object>
	<object>
		<name>1st Premolar</name>
		<pose/>
		<truncated/>
		<difficult/>
		<bndbox>
			<xmin>1231</xmin>
			<xmax>1492</xmax>
			<ymin>121</ymin>
			<ymax>573</ymax>
		</bndbox>
	</object>
	<object>
		<name>2nd Premolar</name>
		<pose/>
		<truncated/>
		<difficult/>
		<bndbox>
			<xmin>1440</xmin>
			<xmax>1639</xmax>
			<ymin>121</ymin>
			<ymax>490</ymax>
		</bndbox>
	</object>
</annotation>
