<?xml version="1.0" ?>
<annotation>
	<filename>Frame_492.jpg</filename>
	<size>
		<width>1920</width>
		<height>1080</height>
		<depth>3</depth>
	</size>
	<object>
		<name>Central Incisor</name>
		<pose/>
		<truncated/>
		<difficult/>
		<bndbox>
			<xmin>955</xmin>
			<xmax>1281</xmax>
			<ymin>238</ymin>
			<ymax>626</ymax>
		</bndbox>
	</object>
	<object>
		<name>Central Incisor</name>
		<pose/>
		<truncated/>
		<difficult/>
		<bndbox>
			<xmin>629</xmin>
			<xmax>955</xmax>
			<ymin>266</ymin>
			<ymax>632</ymax>
		</bndbox>
	</object>
	<object>
		<name>Lateral Incisor</name>
		<pose/>
		<truncated/>
		<difficult/>
		<bndbox>
			<xmin>1281</xmin>
			<xmax>1494</xmax>
			<ymin>223</ymin>
			<ymax>578</ymax>
		</bndbox>
	</object>
	<object>
		<name>Lateral Incisor</name>
		<pose/>
		<truncated/>
		<difficult/>
		<bndbox>
			<xmin>416</xmin>
			<xmax>633</xmax>
			<ymin>281</ymin>
			<ymax>610</ymax>
		</bndbox>
	</object>
	<object>
		<name>Canine</name>
		<pose/>
		<truncated/>
		<difficult/>
		<bndbox>
			<xmin>1494</xmin>
			<xmax>1675</xmax>
			<ymin>195</ymin>
			<ymax>583</ymax>
		</bndbox>
	</object>
	<object>
		<name>Canine</name>
		<pose/>
		<truncated/>
		<difficult/>
		<bndbox>
			<xmin>237</xmin>
			<xmax>412</xmax>
			<ymin>284</ymin>
			<ymax>666</ymax>
		</bndbox>
	</object>
	<object>
		<name>1st Premolar</name>
		<pose/>
		<truncated/>
		<difficult/>
		<bndbox>
			<xmin>1675</xmin>
			<xmax>1793</xmax>
			<ymin>241</ymin>
			<ymax>558</ymax>
		</bndbox>
	</object>
	<object>
		<name>1st Premolar</name>
		<pose/>
		<truncated/>
		<difficult/>
		<bndbox>
			<xmin>135</xmin>
			<xmax>237</xmax>
			<ymin>356</ymin>
			<ymax>655</ymax>
		</bndbox>
	</object>
	<object>
		<name>2nd Premolar</name>
		<pose/>
		<truncated/>
		<difficult/>
		<bndbox>
			<xmin>1793</xmin>
			<xmax>1852</xmax>
			<ymin>302</ymin>
			<ymax>562</ymax>
		</bndbox>
	</object>
	<object>
		<name>2nd Premolar</name>
		<pose/>
		<truncated/>
		<difficult/>
		<bndbox>
			<xmin>65</xmin>
			<xmax>133</xmax>
			<ymin>399</ymin>
			<ymax>650</ymax>
		</bndbox>
	</object>
	<object>
		<name>1st Molar</name>
		<pose/>
		<truncated/>
		<difficult/>
		<bndbox>
			<xmin>1854</xmin>
			<xmax>1892</xmax>
			<ymin>313</ymin>
			<ymax>537</ymax>
		</bndbox>
	</object>
	<object>
		<name>1st Molar</name>
		<pose/>
		<truncated/>
		<difficult/>
		<bndbox>
			<xmin>0</xmin>
			<xmax>61</xmax>
			<ymin>420</ymin>
			<ymax>637</ymax>
		</bndbox>
	</object>
	<object>
		<name>2nd Molar</name>
		<pose/>
		<truncated/>
		<difficult/>
		<bndbox>
			<xmin>1892</xmin>
			<xmax>1919</xmax>
			<ymin>345</ymin>
			<ymax>503</ymax>
		</bndbox>
	</object>
	<object>
		<name>Central Incisor</name>
		<pose/>
		<truncated/>
		<difficult/>
		<bndbox>
			<xmin>998</xmin>
			<xmax>1213</xmax>
			<ymin>718</ymin>
			<ymax>1033</ymax>
		</bndbox>
	</object>
	<object>
		<name>Central Incisor</name>
		<pose/>
		<truncated/>
		<difficult/>
		<bndbox>
			<xmin>796</xmin>
			<xmax>996</xmax>
			<ymin>718</ymin>
			<ymax>1038</ymax>
		</bndbox>
	</object>
	<object>
		<name>Lateral Incisor</name>
		<pose/>
		<truncated/>
		<difficult/>
		<bndbox>
			<xmin>1211</xmin>
			<xmax>1421</xmax>
			<ymin>709</ymin>
			<ymax>1029</ymax>
		</bndbox>
	</object>
	<object>
		<name>Lateral Incisor</name>
		<pose/>
		<truncated/>
		<difficult/>
		<bndbox>
			<xmin>604</xmin>
			<xmax>796</xmax>
			<ymin>730</ymin>
			<ymax>1072</ymax>
		</bndbox>
	</object>
	<object>
		<name>Canine</name>
		<pose/>
		<truncated/>
		<difficult/>
		<bndbox>
			<xmin>1424</xmin>
			<xmax>1612</xmax>
			<ymin>655</ymin>
			<ymax>1063</ymax>
		</bndbox>
	</object>
	<object>
		<name>Canine</name>
		<pose/>
		<truncated/>
		<difficult/>
		<bndbox>
			<xmin>418</xmin>
			<xmax>606</xmax>
			<ymin>727</ymin>
			<ymax>1076</ymax>
		</bndbox>
	</object>
	<object>
		<name>1st Premolar</name>
		<pose/>
		<truncated/>
		<difficult/>
		<bndbox>
			<xmin>1575</xmin>
			<xmax>1756</xmax>
			<ymin>678</ymin>
			<ymax>1017</ymax>
		</bndbox>
	</object>
	<object>
		<name>1st Premolar</name>
		<pose/>
		<truncated/>
		<difficult/>
		<bndbox>
			<xmin>276</xmin>
			<xmax>448</xmax>
			<ymin>757</ymin>
			<ymax>1060</ymax>
		</bndbox>
	</object>
	<object>
		<name>2nd Premolar</name>
		<pose/>
		<truncated/>
		<difficult/>
		<bndbox>
			<xmin>1693</xmin>
			<xmax>1847</xmax>
			<ymin>691</ymin>
			<ymax>952</ymax>
		</bndbox>
	</object>
	<object>
		<name>2nd Premolar</name>
		<pose/>
		<truncated/>
		<difficult/>
		<bndbox>
			<xmin>176</xmin>
			<xmax>319</xmax>
			<ymin>782</ymin>
			<ymax>1026</ymax>
		</bndbox>
	</object>
	<object>
		<name>1st Molar</name>
		<pose/>
		<truncated/>
		<difficult/>
		<bndbox>
			<xmin>1800</xmin>
			<xmax>1920</xmax>
			<ymin>691</ymin>
			<ymax>893</ymax>
		</bndbox>
	</object>
	<object>
		<name>1st Molar</name>
		<pose/>
		<truncated/>
		<difficult/>
		<bndbox>
			<xmin>24</xmin>
			<xmax>217</xmax>
			<ymin>795</ymin>
			<ymax>1010</ymax>
		</bndbox>
	</object>
	<object>
		<name>2nd Molar</name>
		<pose/>
		<truncated/>
		<difficult/>
		<bndbox>
			<xmin>1793</xmin>
			<xmax>1919</xmax>
			<ymin>621</ymin>
			<ymax>691</ymax>
		</bndbox>
	</object>
	<object>
		<name>2nd Molar</name>
		<pose/>
		<truncated/>
		<difficult/>
		<bndbox>
			<xmin>2</xmin>
			<xmax>176</xmax>
			<ymin>732</ymin>
			<ymax>895</ymax>
		</bndbox>
	</object>
	<object>
		<name>3rd Molar</name>
		<pose/>
		<truncated/>
		<difficult/>
		<bndbox>
			<xmin>1843</xmin>
			<xmax>1919</xmax>
			<ymin>573</ymin>
			<ymax>621</ymax>
		</bndbox>
	</object>
	<object>
		<name>3rd Molar</name>
		<pose/>
		<truncated/>
		<difficult/>
		<bndbox>
			<xmin>6</xmin>
			<xmax>117</xmax>
			<ymin>696</ymin>
			<ymax>773</ymax>
		</bndbox>
	</object>
</annotation>
