<?xml version="1.0" ?>
<annotation>
	<filename>Frame_282.jpg</filename>
	<size>
		<width>1920</width>
		<height>1080</height>
		<depth>3</depth>
	</size>
	<object>
		<name>Central Incisor</name>
		<pose/>
		<truncated/>
		<difficult/>
		<bndbox>
			<xmin>645</xmin>
			<xmax>987</xmax>
			<ymin>285</ymin>
			<ymax>656</ymax>
		</bndbox>
	</object>
	<object>
		<name>Central Incisor</name>
		<pose/>
		<truncated/>
		<difficult/>
		<bndbox>
			<xmin>996</xmin>
			<xmax>1326</xmax>
			<ymin>285</ymin>
			<ymax>661</ymax>
		</bndbox>
	</object>
	<object>
		<name>Lateral Incisor</name>
		<pose/>
		<truncated/>
		<difficult/>
		<bndbox>
			<xmin>1329</xmin>
			<xmax>1562</xmax>
			<ymin>280</ymin>
			<ymax>629</ymax>
		</bndbox>
	</object>
	<object>
		<name>Lateral Incisor</name>
		<pose/>
		<truncated/>
		<difficult/>
		<bndbox>
			<xmin>407</xmin>
			<xmax>643</xmax>
			<ymin>296</ymin>
			<ymax>624</ymax>
		</bndbox>
	</object>
	<object>
		<name>Canine</name>
		<pose/>
		<truncated/>
		<difficult/>
		<bndbox>
			<xmin>1566</xmin>
			<xmax>1761</xmax>
			<ymin>276</ymin>
			<ymax>665</ymax>
		</bndbox>
	</object>
	<object>
		<name>Canine</name>
		<pose/>
		<truncated/>
		<difficult/>
		<bndbox>
			<xmin>230</xmin>
			<xmax>405</xmax>
			<ymin>369</ymin>
			<ymax>701</ymax>
		</bndbox>
	</object>
	<object>
		<name>1st Premolar</name>
		<pose/>
		<truncated/>
		<difficult/>
		<bndbox>
			<xmin>1772</xmin>
			<xmax>1892</xmax>
			<ymin>366</ymin>
			<ymax>667</ymax>
		</bndbox>
	</object>
	<object>
		<name>1st Premolar</name>
		<pose/>
		<truncated/>
		<difficult/>
		<bndbox>
			<xmin>119</xmin>
			<xmax>226</xmax>
			<ymin>475</ymin>
			<ymax>704</ymax>
		</bndbox>
	</object>
	<object>
		<name>2nd Premolar</name>
		<pose/>
		<truncated/>
		<difficult/>
		<bndbox>
			<xmin>1863</xmin>
			<xmax>1919</xmax>
			<ymin>464</ymin>
			<ymax>697</ymax>
		</bndbox>
	</object>
	<object>
		<name>2nd Premolar</name>
		<pose/>
		<truncated/>
		<difficult/>
		<bndbox>
			<xmin>29</xmin>
			<xmax>119</xmax>
			<ymin>511</ymin>
			<ymax>715</ymax>
		</bndbox>
	</object>
</annotation>
