<?xml version="1.0" ?>
<annotation>
	<filename>Frame_144.jpg</filename>
	<size>
		<width>1920</width>
		<height>1080</height>
		<depth>3</depth>
	</size>
	<object>
		<name>Central Incisor</name>
		<pose/>
		<truncated/>
		<difficult/>
		<bndbox>
			<xmin>969</xmin>
			<xmax>1313</xmax>
			<ymin>156</ymin>
			<ymax>536</ymax>
		</bndbox>
	</object>
	<object>
		<name>Central Incisor</name>
		<pose/>
		<truncated/>
		<difficult/>
		<bndbox>
			<xmin>615</xmin>
			<xmax>969</xmax>
			<ymin>167</ymin>
			<ymax>529</ymax>
		</bndbox>
	</object>
	<object>
		<name>Lateral Incisor</name>
		<pose/>
		<truncated/>
		<difficult/>
		<bndbox>
			<xmin>1317</xmin>
			<xmax>1541</xmax>
			<ymin>144</ymin>
			<ymax>502</ymax>
		</bndbox>
	</object>
	<object>
		<name>Lateral Incisor</name>
		<pose/>
		<truncated/>
		<difficult/>
		<bndbox>
			<xmin>398</xmin>
			<xmax>618</xmax>
			<ymin>176</ymin>
			<ymax>493</ymax>
		</bndbox>
	</object>
	<object>
		<name>Canine</name>
		<pose/>
		<truncated/>
		<difficult/>
		<bndbox>
			<xmin>1541</xmin>
			<xmax>1736</xmax>
			<ymin>147</ymin>
			<ymax>541</ymax>
		</bndbox>
	</object>
	<object>
		<name>Canine</name>
		<pose/>
		<truncated/>
		<difficult/>
		<bndbox>
			<xmin>212</xmin>
			<xmax>396</xmax>
			<ymin>194</ymin>
			<ymax>563</ymax>
		</bndbox>
	</object>
	<object>
		<name>1st Premolar</name>
		<pose/>
		<truncated/>
		<difficult/>
		<bndbox>
			<xmin>1741</xmin>
			<xmax>1865</xmax>
			<ymin>201</ymin>
			<ymax>529</ymax>
		</bndbox>
	</object>
	<object>
		<name>1st Premolar</name>
		<pose/>
		<truncated/>
		<difficult/>
		<bndbox>
			<xmin>99</xmin>
			<xmax>206</xmax>
			<ymin>267</ymin>
			<ymax>566</ymax>
		</bndbox>
	</object>
	<object>
		<name>2nd Premolar</name>
		<pose/>
		<truncated/>
		<difficult/>
		<bndbox>
			<xmin>1847</xmin>
			<xmax>1919</xmax>
			<ymin>301</ymin>
			<ymax>556</ymax>
		</bndbox>
	</object>
	<object>
		<name>2nd Premolar</name>
		<pose/>
		<truncated/>
		<difficult/>
		<bndbox>
			<xmin>20</xmin>
			<xmax>97</xmax>
			<ymin>314</ymin>
			<ymax>577</ymax>
		</bndbox>
	</object>
	<object>
		<name>Central Incisor</name>
		<pose/>
		<truncated/>
		<difficult/>
		<bndbox>
			<xmin>1052</xmin>
			<xmax>1274</xmax>
			<ymin>683</ymin>
			<ymax>984</ymax>
		</bndbox>
	</object>
	<object>
		<name>Central Incisor</name>
		<pose/>
		<truncated/>
		<difficult/>
		<bndbox>
			<xmin>842</xmin>
			<xmax>1050</xmax>
			<ymin>686</ymin>
			<ymax>989</ymax>
		</bndbox>
	</object>
	<object>
		<name>Lateral Incisor</name>
		<pose/>
		<truncated/>
		<difficult/>
		<bndbox>
			<xmin>1276</xmin>
			<xmax>1476</xmax>
			<ymin>679</ymin>
			<ymax>1034</ymax>
		</bndbox>
	</object>
	<object>
		<name>Lateral Incisor</name>
		<pose/>
		<truncated/>
		<difficult/>
		<bndbox>
			<xmin>629</xmin>
			<xmax>842</xmax>
			<ymin>686</ymin>
			<ymax>1025</ymax>
		</bndbox>
	</object>
	<object>
		<name>Canine</name>
		<pose/>
		<truncated/>
		<difficult/>
		<bndbox>
			<xmin>425</xmin>
			<xmax>624</xmax>
			<ymin>665</ymin>
			<ymax>1080</ymax>
		</bndbox>
	</object>
	<object>
		<name>1st Premolar</name>
		<pose/>
		<truncated/>
		<difficult/>
		<bndbox>
			<xmin>267</xmin>
			<xmax>427</xmax>
			<ymin>701</ymin>
			<ymax>1050</ymax>
		</bndbox>
	</object>
	<object>
		<name>1st Premolar</name>
		<pose/>
		<truncated/>
		<difficult/>
		<bndbox>
			<xmin>1666</xmin>
			<xmax>1829</xmax>
			<ymin>661</ymin>
			<ymax>973</ymax>
		</bndbox>
	</object>
	<object>
		<name>2nd Premolar</name>
		<pose/>
		<truncated/>
		<difficult/>
		<bndbox>
			<xmin>156</xmin>
			<xmax>298</xmax>
			<ymin>735</ymin>
			<ymax>998</ymax>
		</bndbox>
	</object>
	<object>
		<name>2nd Premolar</name>
		<pose/>
		<truncated/>
		<difficult/>
		<bndbox>
			<xmin>1813</xmin>
			<xmax>1920</xmax>
			<ymin>690</ymin>
			<ymax>980</ymax>
		</bndbox>
	</object>
	<object>
		<name>1st Molar</name>
		<pose/>
		<truncated/>
		<difficult/>
		<bndbox>
			<xmin>6</xmin>
			<xmax>194</xmax>
			<ymin>774</ymin>
			<ymax>975</ymax>
		</bndbox>
	</object>
	<object>
		<name>2nd Molar</name>
		<pose/>
		<truncated/>
		<difficult/>
		<bndbox>
			<xmin>0</xmin>
			<xmax>163</xmax>
			<ymin>706</ymin>
			<ymax>858</ymax>
		</bndbox>
	</object>
	<object>
		<name>3rd Molar</name>
		<pose/>
		<truncated/>
		<difficult/>
		<bndbox>
			<xmin>4</xmin>
			<xmax>86</xmax>
			<ymin>672</ymin>
			<ymax>729</ymax>
		</bndbox>
	</object>
</annotation>
